odoo10_addon_l10n_fr_cog-10.0.1.0.0.99.dev4-py3.8-nspkg.pth
odoo/addons/l10n_fr_cog/README.rst
odoo/addons/l10n_fr_cog/__init__.py
odoo/addons/l10n_fr_cog/__manifest__.py
odoo/addons/l10n_fr_cog/post_install.py
odoo/addons/l10n_fr_cog/data/country.xml
odoo/addons/l10n_fr_cog/models/__init__.py
odoo/addons/l10n_fr_cog/models/country.py
odoo/addons/l10n_fr_cog/readme/CONTRIBUTORS.rst
odoo/addons/l10n_fr_cog/readme/DESCRIPTION.rst
odoo/addons/l10n_fr_cog/static/description/icon.png
odoo/addons/l10n_fr_cog/static/description/index.html
odoo/addons/l10n_fr_cog/views/country.xml
odoo10_addon_l10n_fr_cog-10.0.1.0.0.99.dev4.dist-info/METADATA
odoo10_addon_l10n_fr_cog-10.0.1.0.0.99.dev4.dist-info/WHEEL
odoo10_addon_l10n_fr_cog-10.0.1.0.0.99.dev4.dist-info/namespace_packages.txt
odoo10_addon_l10n_fr_cog-10.0.1.0.0.99.dev4.dist-info/top_level.txt
odoo10_addon_l10n_fr_cog-10.0.1.0.0.99.dev4.dist-info/RECORD
